MANIFEST.in
README.md
README.rst
setup.py
thefs.py
thefs.egg-info/PKG-INFO
thefs.egg-info/SOURCES.txt
thefs.egg-info/dependency_links.txt
thefs.egg-info/top_level.txt