Metadata-Version: 1.0
Name: thefs
Version: 0.0.1
Summary: file system assertion plugin for `the`
Home-page: https://github.com/the-py/the-fs
Author: Yan Wenjun
Author-email: mylastnameisyan@gmail.com
License: MIT
Platform: UNKNOWN
Classifier: License :: OSI Approved :: MIT License
Classifier: Topic :: Software Development :: Libraries
